packagechecker/__init__.py
packagechecker/package_checker.py
packagechecker-2.0.dist-info/LICENSE
packagechecker-2.0.dist-info/METADATA
packagechecker-2.0.dist-info/WHEEL
packagechecker-2.0.dist-info/top_level.txt
packagechecker-2.0.dist-info/RECORD
