Metadata-Version: 2.1
Name: packagechecker
Version: 2.0
Summary: Проверка необходимых пакетов, и их установка
Home-page: https://codeberg.org/OneEyedDancer/python-package-checker.git
Author: OneEyedDancer
License: UNKNOWN
Platform: UNKNOWN
Classifier: Programming Language :: Python :: 3
Classifier: License :: OSI Approved :: GNU General Public License v3 or later (GPLv3+)
Classifier: Operating System :: OS Independent
Requires-Python: >=3.5
License-File: LICENSE
